Metadata-Version: 1.0
Name: pro-distributions-func
Version: 1.3
Summary: Gaussian and Binomial distributions
Home-page: UNKNOWN
Author: Mohamed Makram
Author-email: mohamedmakram202@gmail.com
License: UNKNOWN
Platform: UNKNOWN
